maya-stubs/OpenMaya.pyi
maya-stubs/OpenMayaAnim.pyi
maya-stubs/OpenMayaFX.pyi
maya-stubs/OpenMayaMPx.pyi
maya-stubs/OpenMayaRender.pyi
maya-stubs/OpenMayaUI.pyi
maya-stubs/__init__.pyi
maya-stubs/cmds.pyi
maya-stubs/mel.pyi
maya-stubs/standalone.pyi
maya-stubs/api/OpenMaya.pyi
maya-stubs/api/OpenMayaAnim.pyi
maya-stubs/api/OpenMayaRender.pyi
maya-stubs/api/OpenMayaUI.pyi
maya-stubs/api/__init__.pyi
types_maya-0.2.0.dist-info/licenses/LICENSE
types_maya-0.2.0.dist-info/METADATA
types_maya-0.2.0.dist-info/WHEEL
types_maya-0.2.0.dist-info/top_level.txt
types_maya-0.2.0.dist-info/RECORD
