Metadata-Version: 2.4
Name: types-maya
Version: 0.2.0
Summary: External type annotations for Autodesk Maya Python API
Author: Thibaud Gambier
License-Expression: MIT
Project-URL: Repository, https://github.com/tahv/types-maya
Project-URL: PyPI, https://pypi.org/project/types-maya
Classifier: Development Status :: 4 - Beta
Classifier: Intended Audience :: Developers
Classifier: Operating System :: OS Independent
Classifier: Programming Language :: Python :: 3
Classifier: Typing :: Stubs Only
Requires-Python: >=3.7
License-File: LICENSE
Dynamic: license-file
